MANIFEST.in
README.md
setup.py
elf_to_shellcode/__init__.py
elf_to_shellcode/__main__.py
elf_to_shellcode/relocate.py
elf_to_shellcode.egg-info/PKG-INFO
elf_to_shellcode.egg-info/SOURCES.txt
elf_to_shellcode.egg-info/dependency_links.txt
elf_to_shellcode.egg-info/requires.txt
elf_to_shellcode.egg-info/top_level.txt
elf_to_shellcode/arm/__init__.py
elf_to_shellcode/arm/aarch64_dynamic_relocations.py
elf_to_shellcode/arm/arm_32_dynamic_relocations.py
elf_to_shellcode/arm/x32.py
elf_to_shellcode/arm/x64.py
elf_to_shellcode/hooks/__init__.py
elf_to_shellcode/hooks/base_hook.py
elf_to_shellcode/hooks/hooks_configuration_parser.py
elf_to_shellcode/hooks/builtin/__init__.py
elf_to_shellcode/hooks/builtin/change_memory_protection.py
elf_to_shellcode/hooks/builtin/descriptors.py
elf_to_shellcode/hooks/builtin/rwx_bypass.py
elf_to_shellcode/intel/__init__.py
elf_to_shellcode/intel/x32.py
elf_to_shellcode/intel/x64.py
elf_to_shellcode/lib/__init__.py
elf_to_shellcode/lib/consts.py
elf_to_shellcode/lib/exceptions.py
elf_to_shellcode/lib/five.py
elf_to_shellcode/lib/shellcode.py
elf_to_shellcode/lib/ext/__init__.py
elf_to_shellcode/lib/ext/dynamic_relocations_base.py
elf_to_shellcode/lib/ext/dynamic_symbols.py
elf_to_shellcode/lib/ext/irelative_relocations.py
elf_to_shellcode/lib/ext/loader_symbols.py
elf_to_shellcode/lib/utils/__init__.py
elf_to_shellcode/lib/utils/address_utils.py
elf_to_shellcode/lib/utils/disassembler.py
elf_to_shellcode/lib/utils/general.py
elf_to_shellcode/lib/utils/hooks.py
elf_to_shellcode/lib/utils/memory_section.py
elf_to_shellcode/lib/utils/mini_loader.py
elf_to_shellcode/mips/__init__.py
elf_to_shellcode/mips/mips.py
elf_to_shellcode/resources/__init__.py
elf_to_shellcode/resources/mini_loader_arm_x32.shellcode
elf_to_shellcode/resources/mini_loader_arm_x32.shellcode.structs.json
elf_to_shellcode/resources/mini_loader_arm_x32.shellcode.symbols
elf_to_shellcode/resources/mini_loader_arm_x32_dynamic.shellcode
elf_to_shellcode/resources/mini_loader_arm_x32_dynamic.shellcode.structs.json
elf_to_shellcode/resources/mini_loader_arm_x32_dynamic.shellcode.symbols
elf_to_shellcode/resources/mini_loader_arm_x32_dynamic_eshelf.shellcode
