Metadata-Version: 2.1
Name: elf-to-shellcode
Version: 2.2.8
Summary: Python package to create shellcdoes from elfs supported arch (mips, arm (32bit), i386 32bit, i386 64bit, aarch64)
Home-page: https://github.com/jonatanSh/elf_to_shellcode
Author: Jonathan Shimon
Author-email: jonatanshimon@gmail.com
License: MIT License
Platform: UNKNOWN
